maverig/demo.py
maverig/EntryPoint.py
maverig/LICENSE.txt
maverig/README.rst
maverig/requirements.txt
maverig/__init__.py
maverig/data/config.py
maverig/data/dataHandler.py
maverig/data/__init__.py
maverig/data/components/CSV.CHP.json
maverig/data/components/CSV.EV.json
maverig/data/components/CSV.House.json
maverig/data/components/CSV.PV.json
maverig/data/components/CSV.WECS.json
maverig/data/components/PyPower.Branch.json
maverig/data/components/PyPower.PQBus.json
maverig/data/components/PyPower.RefBus.json
maverig/data/components/PyPower.Transformer.json
maverig/data/components/__init__.py
maverig/data/components/default_components/CSV.CHP.json
maverig/data/components/default_components/CSV.EV.json
maverig/data/components/default_components/CSV.House.json
maverig/data/components/default_components/CSV.PV.json
maverig/data/components/default_components/CSV.WECS.json
maverig/data/components/default_components/PyPower.Branch.json
maverig/data/components/default_components/PyPower.PQBus.json
maverig/data/components/default_components/PyPower.RefBus.json
maverig/data/components/default_components/PyPower.Transformer.json
maverig/data/components/icons/agent.svg
maverig/data/components/icons/battery.svg
maverig/data/components/icons/branch.svg
maverig/data/components/icons/bus.svg
maverig/data/components/icons/chp.svg
maverig/data/components/icons/control_strategy.svg
maverig/data/components/icons/ev+battery.svg
maverig/data/components/icons/gas_turbine_power_plant.svg
maverig/data/components/icons/house.svg
maverig/data/components/icons/house2-4.svg
maverig/data/components/icons/house4+.svg
maverig/data/components/icons/large_power_plant.svg
maverig/data/components/icons/market.svg
maverig/data/components/icons/medium_power_plant.svg
maverig/data/components/icons/profile.svg
maverig/data/components/icons/pv.svg
maverig/data/components/icons/pylon.svg
maverig/data/components/icons/refbus.svg
maverig-1.0.5.dist-info/DESCRIPTION.rst
maverig-1.0.5.dist-info/entry_points.txt
maverig-1.0.5.dist-info/METADATA
maverig-1.0.5.dist-info/metadata.json
maverig-1.0.5.dist-info/RECORD
maverig-1.0.5.dist-info/top_level.txt
maverig-1.0.5.dist-info/WHEEL
