Metadata-Version: 2.0
Name: maverig
Version: 1.0.5
Summary: MAVERIG is a visualization component for the mosaik framework
Home-page: https://bitbucket.org/Sash221/maverig
Author: Project MAVERIG
Author-email: pg-maverig@offis.de
License: LGPL
Platform: UNKNOWN
Requires-Dist: PySide (==1.2.2)
Requires-Dist: pyzmq (>=14.3.1)
